{"appleSKU":"","appleTeamID":"","enableCodelessAutoInitialization":true,"enableUnityGamingServicesAutoInitialization":false,"products":[{"id":"com.game.iap.coin150","type":0,"storeIDs":[],"defaultDescription":{"googleLocale":4,"title":"150 Coins","description":"Buy 150 coins"},"screenshotPath":"","applePriceTier":0,"googlePrice":{"data":[99,0,0,131072],"num":0.99},"pricingTemplateID":"0.99","descriptions":[],"udpPrice":{"data":[0,0,0,0],"num":0.0},"payouts":[]},{"id":"com.game.iap.coin500","type":0,"storeIDs":[],"defaultDescription":{"googleLocale":4,"title":"500 Coins","description":"Buy 500 coins"},"screenshotPath":"","applePriceTier":0,"googlePrice":{"data":[199,0,0,131072],"num":1.99},"pricingTemplateID":"1.99","descriptions":[],"udpPrice":{"data":[0,0,0,0],"num":0.0},"payouts":[]},{"id":"com.game.iap.coin1000","type":0,"storeIDs":[],"defaultDescription":{"googleLocale":4,"title":"1000 Coins","description":"Buy 1000 coins"},"screenshotPath":"","applePriceTier":0,"googlePrice":{"data":[299,0,0,131072],"num":2.99},"pricingTemplateID":"2.99","descriptions":[],"udpPrice":{"data":[0,0,0,0],"num":0.0},"payouts":[]},{"id":"com.game.iap.coin2000","type":0,"storeIDs":[],"defaultDescription":{"googleLocale":4,"title":"2000 Coins","description":"Buy 2000 coins"},"screenshotPath":"","applePriceTier":0,"googlePrice":{"data":[499,0,0,131072],"num":4.99},"pricingTemplateID":"4.99","descriptions":[],"udpPrice":{"data":[0,0,0,0],"num":0.0},"payouts":[]},{"id":"com.game.iap.coin4000","type":0,"storeIDs":[],"defaultDescription":{"googleLocale":4,"title":"4000 Coins","description":"Buy 4000 coins"},"screenshotPath":"","applePriceTier":0,"googlePrice":{"data":[799,0,0,131072],"num":7.99},"pricingTemplateID":"7.99","descriptions":[],"udpPrice":{"data":[0,0,0,0],"num":0.0},"payouts":[]},{"id":"com.game.iap.coin8000","type":0,"storeIDs":[],"defaultDescription":{"googleLocale":4,"title":"8000 Coins","description":"Buy 8000 coins"},"screenshotPath":"","applePriceTier":0,"googlePrice":{"data":[1299,0,0,131072],"num":12.99},"pricingTemplateID":"12.99","descriptions":[],"udpPrice":{"data":[0,0,0,0],"num":0.0},"payouts":[]}]}
